svs/__init__.py
svs/kb.py
svs/py.typed
svs/types.py
svs/util.py
svs/embeddings/__init__.py
svs/embeddings/mock.py
svs/embeddings/ollama.py
svs/embeddings/openai.py
svs/embeddings/util.py
svs-0.7.4.dist-info/METADATA
svs-0.7.4.dist-info/WHEEL
svs-0.7.4.dist-info/licenses/LICENSE.txt
svs-0.7.4.dist-info/RECORD
